CHANGES.txt
INSTALL.txt
LICENSE.txt
MANIFEST.in
README.txt
setup.py
cloud_browser/__init__.py
cloud_browser/app_settings.py
cloud_browser/common.py
cloud_browser/errors.py
cloud_browser/models.py
cloud_browser/tests.py
cloud_browser/urls.py
cloud_browser/urls_admin.py
cloud_browser/views.py
cloud_browser/cloud/__init__.py
cloud_browser/cloud/apache_libcloud.py
cloud_browser/cloud/aws.py
cloud_browser/cloud/base.py
cloud_browser/cloud/boto_base.py
cloud_browser/cloud/config.py
cloud_browser/cloud/errors.py
cloud_browser/cloud/fs.py
cloud_browser/cloud/google.py
cloud_browser/cloud/rackspace.py
cloud_browser/media/css/cloud-browser-admin.css
cloud_browser/media/css/cloud-browser.css
cloud_browser/media/img/tango/AUTHORS
cloud_browser/media/img/tango/COPYING
cloud_browser/media/img/tango/README
cloud_browser/media/img/tango/16x16/animations/process-working.png
cloud_browser/media/img/tango/16x16/emblems/emblem-favorite.png
cloud_browser/media/img/tango/16x16/emblems/emblem-important.png
cloud_browser/media/img/tango/16x16/emblems/emblem-photos.png
cloud_browser/media/img/tango/16x16/emblems/emblem-readonly.png
cloud_browser/media/img/tango/16x16/emblems/emblem-symbolic-link.png
cloud_browser/media/img/tango/16x16/emblems/emblem-system.png
cloud_browser/media/img/tango/16x16/emblems/emblem-unreadable.png
cloud_browser/media/img/tango/16x16/mimetypes/text-html.png
cloud_browser/media/img/tango/16x16/mimetypes/text-x-generic-template.png
cloud_browser/media/img/tango/16x16/mimetypes/text-x-generic.png
cloud_browser/media/img/tango/16x16/mimetypes/text-x-script.png
cloud_browser/media/img/tango/16x16/mimetypes/video-x-generic.png
cloud_browser/media/img/tango/16x16/mimetypes/x-office-document.png
cloud_browser/media/img/tango/16x16/mimetypes/x-office-drawing.png
cloud_browser/media/img/tango/16x16/mimetypes/x-office-presentation.png
cloud_browser/media/img/tango/16x16/mimetypes/x-office-spreadsheet.png
cloud_browser/media/img/tango/16x16/places/folder-remote.png
django_cloud_browser.egg-info/PKG-INFO
django_cloud_browser.egg-info/SOURCES.txt
django_cloud_browser.egg-info/dependency_links.txt
django_cloud_browser.egg-info/requires.txt
django_cloud_browser.egg-info/top_level.txt