Metadata-Version: 1.1
Name: django-cloud-browser
Version: 0.5.0
Summary: Django Cloud Browser application.
Home-page: http://ryan-roemer.github.com/django-cloud-browser
Author: Ryan Roemer
Author-email: ryan@loose-bits.com
License: UNKNOWN
Platform: UNKNOWN
Classifier: Development Status :: 4 - Beta
Classifier: Environment :: Web Environment
Classifier: Framework :: Django
Classifier: Intended Audience :: Developers
Classifier: Intended Audience :: System Administrators
Classifier: License :: OSI Approved :: MIT License
Classifier: Operating System :: OS Independent
Classifier: Programming Language :: Python
Classifier: Topic :: Internet
Classifier: Topic :: Internet :: WWW/HTTP :: Site Management
